{
    "1": {
        "name": "Knives Out",
        "year": "2019",
        "runtime": "N/A",
        "certificate": "N/A",
        "rating": "7.9"
    },
    "2": {
        "name": "Klaus",
        "year": "2019",
        "runtime": "N/A",
        "certificate": "N/A",
        "rating": "8.2"
    },
    "3": {
        "name": "Last Christmas",
        "year": "2019",
        "runtime": "N/A",
        "certificate": "N/A",
        "rating": "6.5"
    },
    "4": {
        "name": "It: Chapter Two",
        "year": "2019",
        "runtime": "N/A",
        "certificate": "N/A",
        "rating": "6.5"
    },
    "5": {
        "name": "Parasite",
        "year": "2019",
        "runtime": "N/A",
        "certificate": "N/A",
        "rating": "8.5"
    },
    "6": {
        "name": "Once Upon a Time... in Hollywood",
        "year": "2019",
        "runtime": "N/A",
        "certificate": "N/A",
        "rating": "7.6"
    },
    "7": {
        "name": "Avengers: Endgame",
        "year": "2019",
        "runtime": "N/A",
        "certificate": "N/A",
        "rating": "8.4"
    },
    "8": {
        "name": "The Hustle",
        "year": "2019",
        "runtime": "N/A",
        "certificate": "N/A",
        "rating": "5.5"
    },
    "9": {
        "name": "The Gentlemen",
        "year": "2019",
        "runtime": "N/A",
        "certificate": "N/A",
        "rating": "7.8"
    },
    "10": {
        "name": "Little Women",
        "year": "2019",
        "runtime": "N/A",
        "certificate": "N/A",
        "rating": "7.8"
    },
    "11": {
        "name": "Ford v Ferrari",
        "year": "2019",
        "runtime": "N/A",
        "certificate": "N/A",
        "rating": "8.1"
    },
    "12": {
        "name": "Doctor Sleep",
        "year": "2019",
        "runtime": "N/A",
        "certificate": "N/A",
        "rating": "7.3"
    },
    "13": {
        "name": "Ready or Not",
        "year": "2019",
        "runtime": "N/A",
        "certificate": "N/A",
        "rating": "6.8"
    },
    "14": {
        "name": "Bombshell",
        "year": "2019",
        "runtime": "N/A",
        "certificate": "N/A",
        "rating": "6.8"
    },
    "15": {
        "name": "1917",
        "year": "2019",
        "runtime": "N/A",
        "certificate": "N/A",
        "rating": "8.2"
    },
    "16": {
        "name": "Joker",
        "year": "2019",
        "runtime": "N/A",
        "certificate": "N/A",
        "rating": "8.3"
    },
    "17": {
        "name": "Midsommar",
        "year": "2019",
        "runtime": "N/A",
        "certificate": "N/A",
        "rating": "7.1"
    },
    "18": {
        "name": "The Irishman",
        "year": "2019",
        "runtime": "N/A",
        "certificate": "N/A",
        "rating": "7.8"
    },
    "19": {
        "name": "Uncut Gems",
        "year": "2019",
        "runtime": "N/A",
        "certificate": "N/A",
        "rating": "7.4"
    },
    "20": {
        "name": "Noelle",
        "year": "2019",
        "runtime": "N/A",
        "certificate": "N/A",
        "rating": "6.3"
    },
    "21": {
        "name": "Brightburn",
        "year": "2019",
        "runtime": "N/A",
        "certificate": "N/A",
        "rating": "6.1"
    },
    "22": {
        "name": "The King",
        "year": "2019",
        "runtime": "N/A",
        "certificate": "N/A",
        "rating": "7.3"
    },
    "23": {
        "name": "The Fanatic",
        "year": "2019",
        "runtime": "N/A",
        "certificate": "N/A",
        "rating": "4.1"
    },
    "24": {
        "name": "Star Wars: Episode IX - The Rise of Skywalker",
        "year": "2019",
        "runtime": "N/A",
        "certificate": "N/A",
        "rating": "6.4"
    },
    "25": {
        "name": "El Camino",
        "year": "2019",
        "runtime": "N/A",
        "certificate": "N/A",
        "rating": "7.3"
    }
}