{
    "1": {
        "name": "Eyes Wide Shut",
        "year": "1999",
        "runtime": "N/A",
        "certificate": "N/A",
        "rating": "7.5"
    },
    "2": {
        "name": "Fight Club",
        "year": "1999",
        "runtime": "N/A",
        "certificate": "N/A",
        "rating": "8.8"
    },
    "3": {
        "name": "The Matrix",
        "year": "1999",
        "runtime": "N/A",
        "certificate": "N/A",
        "rating": "8.7"
    },
    "4": {
        "name": "The Green Mile",
        "year": "1999",
        "runtime": "N/A",
        "certificate": "N/A",
        "rating": "8.6"
    },
    "5": {
        "name": "American Beauty",
        "year": "1999",
        "runtime": "N/A",
        "certificate": "N/A",
        "rating": "8.3"
    },
    "6": {
        "name": "The Sixth Sense",
        "year": "1999",
        "runtime": "N/A",
        "certificate": "N/A",
        "rating": "8.2"
    },
    "7": {
        "name": "10 Things I Hate About You",
        "year": "1999",
        "runtime": "N/A",
        "certificate": "N/A",
        "rating": "7.4"
    },
    "8": {
        "name": "The Mummy",
        "year": "1999",
        "runtime": "N/A",
        "certificate": "N/A",
        "rating": "7.1"
    },
    "9": {
        "name": "American Pie",
        "year": "1999",
        "runtime": "N/A",
        "certificate": "N/A",
        "rating": "7.0"
    },
    "10": {
        "name": "Magnolia",
        "year": "1999",
        "runtime": "N/A",
        "certificate": "N/A",
        "rating": "8.0"
    },
    "11": {
        "name": "Dogma",
        "year": "1999",
        "runtime": "N/A",
        "certificate": "N/A",
        "rating": "7.3"
    },
    "12": {
        "name": "Notting Hill",
        "year": "1999",
        "runtime": "N/A",
        "certificate": "N/A",
        "rating": "7.2"
    },
    "13": {
        "name": "Star Wars: Episode I - The Phantom Menace",
        "year": "1999",
        "runtime": "N/A",
        "certificate": "N/A",
        "rating": "6.5"
    },
    "14": {
        "name": "Blue Streak",
        "year": "1999",
        "runtime": "N/A",
        "certificate": "N/A",
        "rating": "6.4"
    },
    "15": {
        "name": "Office Space",
        "year": "1999",
        "runtime": "N/A",
        "certificate": "N/A",
        "rating": "7.6"
    },
    "16": {
        "name": "Stigmata",
        "year": "1999",
        "runtime": "N/A",
        "certificate": "N/A",
        "rating": "6.2"
    },
    "17": {
        "name": "The Talented Mr. Ripley",
        "year": "1999",
        "runtime": "N/A",
        "certificate": "N/A",
        "rating": "7.4"
    },
    "18": {
        "name": "Cruel Intentions",
        "year": "1999",
        "runtime": "N/A",
        "certificate": "N/A",
        "rating": "6.8"
    },
    "19": {
        "name": "Toy Story 2",
        "year": "1999",
        "runtime": "N/A",
        "certificate": "N/A",
        "rating": "7.9"
    },
    "20": {
        "name": "Election",
        "year": "1999",
        "runtime": "N/A",
        "certificate": "N/A",
        "rating": "7.2"
    },
    "21": {
        "name": "Girl, Interrupted",
        "year": "1999",
        "runtime": "N/A",
        "certificate": "N/A",
        "rating": "7.3"
    },
    "22": {
        "name": "Romance",
        "year": "1999",
        "runtime": "N/A",
        "certificate": "N/A",
        "rating": "5.2"
    },
    "23": {
        "name": "October Sky",
        "year": "1999",
        "runtime": "N/A",
        "certificate": "N/A",
        "rating": "7.8"
    },
    "24": {
        "name": "The Insider",
        "year": "1999",
        "runtime": "N/A",
        "certificate": "N/A",
        "rating": "7.8"
    },
    "25": {
        "name": "The Iron Giant",
        "year": "1999",
        "runtime": "N/A",
        "certificate": "N/A",
        "rating": "8.1"
    }
}