{
    "1": {
        "name": "One Flew Over the Cuckoo's Nest",
        "year": "1975",
        "runtime": "N/A",
        "certificate": "N/A",
        "rating": "8.6"
    },
    "2": {
        "name": "Sal\u00f2, or the 120 Days of Sodom",
        "year": "1975",
        "runtime": "N/A",
        "certificate": "N/A",
        "rating": "5.8"
    },
    "3": {
        "name": "Jaws",
        "year": "1975",
        "runtime": "N/A",
        "certificate": "N/A",
        "rating": "8.1"
    },
    "4": {
        "name": "Barry Lyndon",
        "year": "1975",
        "runtime": "N/A",
        "certificate": "N/A",
        "rating": "8.1"
    },
    "5": {
        "name": "Monty Python and the Holy Grail",
        "year": "1975",
        "runtime": "N/A",
        "certificate": "N/A",
        "rating": "8.2"
    },
    "6": {
        "name": "The Rocky Horror Picture Show",
        "year": "1975",
        "runtime": "N/A",
        "certificate": "N/A",
        "rating": "7.4"
    },
    "7": {
        "name": "Dog Day Afternoon",
        "year": "1975",
        "runtime": "N/A",
        "certificate": "N/A",
        "rating": "8.0"
    },
    "8": {
        "name": "Sholay",
        "year": "1975",
        "runtime": "N/A",
        "certificate": "N/A",
        "rating": "8.1"
    },
    "9": {
        "name": "Three Days of the Condor",
        "year": "1975",
        "runtime": "N/A",
        "certificate": "N/A",
        "rating": "7.4"
    },
    "10": {
        "name": "Shampoo",
        "year": "1975",
        "runtime": "N/A",
        "certificate": "N/A",
        "rating": "6.4"
    },
    "11": {
        "name": "Mirror",
        "year": "1975",
        "runtime": "N/A",
        "certificate": "N/A",
        "rating": "7.9"
    },
    "12": {
        "name": "The Chaos Class Failed the Class",
        "year": "1975",
        "runtime": "N/A",
        "certificate": "N/A",
        "rating": "8.5"
    },
    "13": {
        "name": "Nashville",
        "year": "1975",
        "runtime": "N/A",
        "certificate": "N/A",
        "rating": "7.6"
    },
    "14": {
        "name": "Picnic at Hanging Rock",
        "year": "1975",
        "runtime": "N/A",
        "certificate": "N/A",
        "rating": "7.4"
    },
    "15": {
        "name": "The Chaos Class",
        "year": "1975",
        "runtime": "N/A",
        "certificate": "N/A",
        "rating": "9.2"
    },
    "16": {
        "name": "The Man Who Would Be King",
        "year": "1975",
        "runtime": "N/A",
        "certificate": "N/A",
        "rating": "7.7"
    },
    "17": {
        "name": "Night Moves",
        "year": "1975",
        "runtime": "N/A",
        "certificate": "N/A",
        "rating": "7.1"
    },
    "18": {
        "name": "Dersu Uzala",
        "year": "1975",
        "runtime": "N/A",
        "certificate": "N/A",
        "rating": "8.2"
    },
    "19": {
        "name": "Tommy",
        "year": "1975",
        "runtime": "N/A",
        "certificate": "N/A",
        "rating": "6.6"
    },
    "20": {
        "name": "Hard Times",
        "year": "1975",
        "runtime": "N/A",
        "certificate": "N/A",
        "rating": "7.2"
    },
    "21": {
        "name": "Death Race 2000",
        "year": "1975",
        "runtime": "N/A",
        "certificate": "N/A",
        "rating": "6.2"
    },
    "22": {
        "name": "Supervixens",
        "year": "1975",
        "runtime": "N/A",
        "certificate": "N/A",
        "rating": "5.9"
    },
    "23": {
        "name": "The Passenger",
        "year": "1975",
        "runtime": "N/A",
        "certificate": "N/A",
        "rating": "7.4"
    },
    "24": {
        "name": "Deep Red",
        "year": "1975",
        "runtime": "N/A",
        "certificate": "N/A",
        "rating": "7.5"
    },
    "25": {
        "name": "The Return of the Pink Panther",
        "year": "1975",
        "runtime": "N/A",
        "certificate": "N/A",
        "rating": "7.0"
    }
}